{
  "name": "WF7_Distributed_Lock_System",
  "nodes": [
    {
      "parameters": {
        "httpMethod": "POST",
        "path": "acquire-lock",
        "options": {}
      },
      "name": "Webhook",
      "type": "n8n-nodes-base.webhook",
      "typeVersion": 2.1,
      "position": [
        0,
        0
      ],
      "webhookId": "acquire-lock"
    },
    {
      "parameters": {
        "jsCode": "// Acquire Lock with TTL - FASE 1.1\n// Input: { provider_id, start_time, lock_duration_minutes? }\n// Output: { success, lock_id, acquired, message, expires_at }\n\nconst input = $input.first().json;\n\n// Validación de input\nif (!input.provider_id || !input.start_time) {\n  throw new Error('Missing required fields: provider_id, start_time');\n}\n\nconst lockDuration = input.lock_duration_minutes || 5; // Default 5 min TTL\nconst lockKey = `lock_${input.provider_id}_${input.start_time}`;\n\nreturn [{\n  json: {\n    provider_id: input.provider_id,\n    start_time: input.start_time,\n    lock_key: lockKey,\n    expires_at: `NOW() + INTERVAL '${lockDuration} minutes'`,\n    lock_duration_minutes: lockDuration\n  }\n}];"
      },
      "name": "Build Lock Query",
      "type": "n8n-nodes-base.code",
      "typeVersion": 2,
      "position": [
        256,
        0
      ]
    },
    {
      "parameters": {
        "operation": "executeQuery",
        "query": "INSERT INTO booking_locks (provider_id, start_time, lock_key, acquired_at, expires_at) VALUES ($1::int, $2::timestamp, $3::text, NOW(), NOW() + INTERVAL '5 minutes') ON CONFLICT (lock_key) DO UPDATE SET acquired_at = NOW(), expires_at = NOW() + INTERVAL '5 minutes' RETURNING lock_id, lock_key, acquired_at, expires_at, (acquired_at > NOW() - INTERVAL '5 minutes') as is_valid;",
        "options": {
          "queryReplacement": "={{ $json.provider_id }}, {{ $json.start_time }}, {{ $json.lock_key }}"
        }
      },
      "name": "Acquire Lock",
      "type": "n8n-nodes-base.postgres",
      "typeVersion": 2.6,
      "position": [
        512,
        0
      ],
      "credentials": {
        "postgres": {
          "id": "SFNQsmuu4zirZAnP",
          "name": "Postgres account"
        }
      }
    },
    {
      "parameters": {
        "httpMethod": "POST",
        "path": "release-lock",
        "options": {}
      },
      "name": "Release Lock Webhook",
      "type": "n8n-nodes-base.webhook",
      "typeVersion": 2.1,
      "position": [
        0,
        304
      ],
      "webhookId": "release-lock"
    },
    {
      "parameters": {
        "operation": "executeQuery",
        "query": "DELETE FROM booking_locks WHERE lock_id = $1::int OR lock_key = $2::text;",
        "options": {
          "queryReplacement": "={{ $json.lock_id ?? '' }}, {{ $json.lock_key ?? '' }}"
        }
      },
      "name": "Release Lock",
      "type": "n8n-nodes-base.postgres",
      "typeVersion": 2.6,
      "position": [
        256,
        304
      ],
      "credentials": {
        "postgres": {
          "id": "SFNQsmuu4zirZAnP",
          "name": "Postgres account"
        }
      }
    },
    {
      "parameters": {
        "jsCode": "// Standard Contract Output for Lock System\nconst input = $input.first().json;\n\nreturn [{\n  json: {\n    success: true,\n    error_code: null,\n    error_message: null,\n    data: {\n      lock_id: input.lock_id,\n      lock_key: input.lock_key,\n      acquired_at: input.acquired_at,\n      expires_at: input.expires_at,\n      is_valid: input.is_valid !== false\n    },\n    _meta: {\n      source: 'WF7_DISTRIBUTED_LOCK_SYSTEM',\n      timestamp: new Date().toISOString(),\n      version: '1.1.0'\n    }\n  }\n}];"
      },
      "name": "Standard Contract Output",
      "type": "n8n-nodes-base.code",
      "typeVersion": 2,
      "position": [
        752,
        0
      ]
    }
  ],
  "connections": {
    "Webhook": {
      "main": [
        [
          {
            "node": "Build Lock Query",
            "type": "main",
            "index": 0
          }
        ]
      ]
    },
    "Build Lock Query": {
      "main": [
        [
          {
            "node": "Acquire Lock",
            "type": "main",
            "index": 0
          }
        ]
      ]
    },
    "Acquire Lock": {
      "main": [
        [
          {
            "node": "Standard Contract Output",
            "type": "main",
            "index": 0
          }
        ]
      ]
    },
    "Release Lock Webhook": {
      "main": [
        [
          {
            "node": "Release Lock",
            "type": "main",
            "index": 0
          }
        ]
      ]
    }
  },
  "settings": {
    "executionOrder": "v1",
    "binaryMode": "separate",
    "availableInMCP": false,
    "callerPolicy": "workflowsFromSameOwner"
  },
  "active": true,
  "versionId": "49bd9645-2df8-4490-b2cd-d6b1ae9680b2"
}
